{
  "merchant_name": {
    "value": "FOOD STREET",
    "confidence": 0.9
  },
  "transaction_date": {
    "value": "19-01-2023",
    "confidence": 0.9
  },
  "transaction_time": {
    "value": "14:42:00",
    "confidence": 0.9
  },
  "items": [
    {
      "description": {
        "value": "K23 - Thai Food",
        "confidence": 0.9
      },
      "quantity": {
        "value": 1,
        "confidence": 0.9
      },
      "total_price": {
        "value": 60.0,
        "confidence": 0.9
      }
    }
  ],
  "total": {
    "value": 60.0,
    "confidence": 0.9
  },
  "tax_id": {
    "value": "010553049786",
    "confidence": 0.9
  },
  "receipt_no": {
    "value": "K.0350",
    "confidence": 0.9
  },
  "address": null,
  "discount": 0,
  "status": false,
  "hashed_receipt": "Shop23"
}